unrolr/__init__.py
unrolr/core/__init__.py
unrolr/core/kernel.cl
unrolr/core/pca.py
unrolr/core/spe_cpu.py
unrolr/core/spe_opencl.py
unrolr/core/unrolr.py
unrolr/feature_extraction/__init__.py
unrolr/feature_extraction/dihedrals.py
unrolr/feature_extraction/intramolecular_distances.py
unrolr/plotting/__init__.py
unrolr/plotting/plot_embedding.py
unrolr/plotting/plot_sampling.py
unrolr/sampling/__init__.py
unrolr/sampling/sampling.py
unrolr/utils/__init__.py
unrolr/utils/utils.py
unrolr-0.5.0.3.dist-info/LICENSE
unrolr-0.5.0.3.dist-info/WHEEL
unrolr-0.5.0.3.dist-info/METADATA
unrolr-0.5.0.3.dist-info/RECORD
