Metadata-Version: 2.1
Name: unrolr
Version: 0.5.0.3
Summary: Dimensionality reduction method for MD trajectories
Home-page: https://github.com/jeeberhardt/unrolr
License: MIT
Keywords: bioinformatics,molecular structures,molecular dynamics,OpenCL,dimensionality reduction,stochastic proximity embedding,dihedral angles
Author: jeeberhardt
Author-email: qksoneo@gmail.com
Requires-Python: >=3.6
Classifier: License :: OSI Approved :: MIT License
Classifier: Operating System :: MacOS
Classifier: Operating System :: Unix
Classifier: Programming Language :: Python :: 3
Classifier: Programming Language :: Python :: 3.6
Classifier: Programming Language :: Python :: 3.7
Classifier: Programming Language :: Python :: 3.8
Classifier: Topic :: Scientific/Engineering
Requires-Dist: MDAnalysis (>=0.17.0)
Requires-Dist: h5py (>=2.5.0)
Requires-Dist: matplotlib (>=1.4.3)
Requires-Dist: numpy (>=1.11.3)
Requires-Dist: pandas (>=0.17.1)
Requires-Dist: pyopencl (>=2015.1)
Requires-Dist: scipy (>=1.2.1)
Project-URL: Repository, https://github.com/jeeberhardt/unrolr
